AutoPilot/Board.py
AutoPilot/__init__.py
tests/__init__.py
tests/test_board.py
PiAutoPilot-0.0.2.dist-info/LICENSE
PiAutoPilot-0.0.2.dist-info/METADATA
PiAutoPilot-0.0.2.dist-info/WHEEL
PiAutoPilot-0.0.2.dist-info/top_level.txt
PiAutoPilot-0.0.2.dist-info/RECORD
