Metadata-Version: 2.1
Name: PiAutoPilot
Version: 0.0.2
Summary: Autopilot for RaspberryPi connected to F7 Flight Controller
Home-page: https://github.com/ksanthanam/PiAutoPilot
Author: KK Santhanam
Author-email: KK.Santhanam@gmail.com
License: MIT License
